[
    {
        "id": "bordeaux-getaway",
        "image": "/img/listing/01.jpg",
        "subtitle": "Entire home in Bordeaux",
        "title": "Bordeaux Getaway",
        "details": [
            "4-6 guests",
            "Entire Home",
            "5 beds",
            "3 bath Wifi",
            "Kitchen",
            "Free Parking"
        ],
        "rating": 5.0,
        "reviews": 318,
        "pricePerNight": 325,
        "currency": "$",
        "isFavorite": true
    },
    {
        "id": "charming-waterfront-condo",
        "image": "/img/listing/02.jpg",
        "subtitle": "Entire home in Bordeaux",
        "title": "Charming Waterfront Condo",
        "details": [
            "4-6 guests",
            "Entire Home",
            "5 beds",
            "3 bath Wifi",
            "Kitchen",
            "Free Parking"
        ],
        "rating": 5.0,
        "reviews": 318,
        "pricePerNight": 200,
        "currency": "$",
        "isFavorite": false
    },
    {
        "id": "historic-city-center-home",
        "image": "/img/listing/03.jpg",
        "subtitle": "Entire home in Bordeaux",
        "title": "Historic City tCenter Home",
        "details": [
            "4-4 guests",
            "Entire Home",
            "5 beds",
            "3 bath Wifi",
            "Kitchen",
            "Free Parking"
        ],
        "rating": 5.0,
        "reviews": 318,
        "pricePerNight": 125,
        "currency": "$",
        "isFavorite": false
    }
]